{
  "id": "dc28e234-1f7c-4a65-9587-8210ec4eb325",
  "title": "\u56fd\u4ea7GPU\u5386\u53f2\u6027\u65f6\u523b\uff01\u6469\u5c14\u7ebf\u7a0b\u3001\u6c90\u66e6\u540c\u65e5\u83b7IPO\u53d7\u7406",
  "content": "\u90fd\u5728\u7528\u81ea\u5df1\u7684\u65b9\u5f0f\u8bb2\u8ff0\u7740\u56fd\u4ea7GPU\u5d1b\u8d77\u7684\u6545\u4e8b",
  "url": "https://www.qbitai.com/2025/07/303642.html",
  "source_id": "014222ee-da63-44bf-b685-c3232e8d3e1f",
  "category": "chinese-ai-news",
  "author": "\u68a6\u6668",
  "published_at": null,
  "created_at": "2025-07-01T16:55:18.572227",
  "quality_score": 0.8999999999999999,
  "metadata": {
    "workflow_id": "15333d42-b6a3-4b3f-8c33-91b70037ccf5",
    "extraction_method": "rss",
    "original_item": {
      "title": "\u56fd\u4ea7GPU\u5386\u53f2\u6027\u65f6\u523b\uff01\u6469\u5c14\u7ebf\u7a0b\u3001\u6c90\u66e6\u540c\u65e5\u83b7IPO\u53d7\u7406",
      "content": "\u90fd\u5728\u7528\u81ea\u5df1\u7684\u65b9\u5f0f\u8bb2\u8ff0\u7740\u56fd\u4ea7GPU\u5d1b\u8d77\u7684\u6545\u4e8b",
      "url": "https://www.qbitai.com/2025/07/303642.html",
      "author": "\u68a6\u6668",
      "published": "Tue, 01 Jul 2025 08:13:56 +0000",
      "category": "chinese-ai-news",
      "source_id": "014222ee-da63-44bf-b685-c3232e8d3e1f",
      "extraction_method": "rss"
    }
  }
}